{
  "description": "Training log for sequential relay models — 16-class 2D vs 4-class per-axis QAM16 classification",
  "timestamp": "2026-03-24",
  "device": "cuda (NVIDIA GeForce GTX 1660 SUPER)",
  "modulation": "qam16",
  "seed": 42,
  "training_snrs": [5, 10, 15, 20, 25],
  "mc_bits": 10000,
  "mc_trials": 10,
  "eval_snrs": [0, 2, 4, 6, 8, 10, 12, 14, 16, 18, 20],
  "pre_loaded_variants": ["MLP 4-cls", "MLP 16-cls", "VAE 4-cls", "VAE 16-cls", "CGAN 4-cls", "CGAN 16-cls", "Hybrid 4-cls", "Hybrid 16-cls"],
  "training_runs": {
    "Transformer 4-cls": {
      "params": 17748,
      "architecture": "5-token Transformer",
      "d_model": 32,
      "heads": 4,
      "in_channels": 1,
      "layers": 2,
      "epochs": 100,
      "samples": 50000,
      "train_samples": 42483,
      "val_samples": 7497,
      "classify_2d": false,
      "final_loss": 0.250029,
      "best_loss": 0.250029,
      "final_train_acc": 0.9082,
      "final_val_acc": 0.9089,
      "ber_at_20dB": 0.008100,
      "avg_ber": 0.163337,
      "training_history": [
        {"epoch": 1, "loss": 0.372947, "train_acc": 0.9047, "val_acc": 0.9040},
        {"epoch": 10, "loss": 0.277365, "train_acc": 0.9089, "val_acc": 0.9090},
        {"epoch": 20, "loss": 0.267382, "train_acc": 0.9074, "val_acc": 0.9088},
        {"epoch": 30, "loss": 0.260661, "train_acc": 0.9072, "val_acc": 0.9090},
        {"epoch": 40, "loss": 0.257873, "train_acc": 0.9073, "val_acc": 0.9084},
        {"epoch": 50, "loss": 0.256385, "train_acc": 0.9081, "val_acc": 0.9097},
        {"epoch": 60, "loss": 0.254764, "train_acc": 0.9085, "val_acc": 0.9100},
        {"epoch": 70, "loss": 0.253471, "train_acc": 0.9088, "val_acc": 0.9073},
        {"epoch": 80, "loss": 0.252117, "train_acc": 0.9094, "val_acc": 0.9093},
        {"epoch": 90, "loss": 0.251237, "train_acc": 0.9085, "val_acc": 0.9074},
        {"epoch": 100, "loss": 0.250029, "train_acc": 0.9082, "val_acc": 0.9089}
      ]
    },
    "Transformer 16-cls": {
      "params": 17984,
      "architecture": "5-token Transformer",
      "d_model": 32,
      "heads": 4,
      "in_channels": 2,
      "layers": 2,
      "epochs": 200,
      "samples": 50000,
      "train_samples": 42500,
      "val_samples": 7500,
      "classify_2d": true,
      "final_loss": 0.458851,
      "best_loss": 0.456994,
      "final_train_acc": 0.8495,
      "final_val_acc": 0.8388,
      "ber_at_20dB": 0.000010,
      "avg_ber": 0.145457,
      "training_history": [
        {"epoch": 1, "loss": 0.957382, "train_acc": 0.8404, "val_acc": 0.8376},
        {"epoch": 20, "loss": 0.503411, "train_acc": 0.8436, "val_acc": 0.8409},
        {"epoch": 40, "loss": 0.487945, "train_acc": 0.8424, "val_acc": 0.8392},
        {"epoch": 60, "loss": 0.481139, "train_acc": 0.8443, "val_acc": 0.8387},
        {"epoch": 80, "loss": 0.475845, "train_acc": 0.8456, "val_acc": 0.8408},
        {"epoch": 100, "loss": 0.471729, "train_acc": 0.8456, "val_acc": 0.8389},
        {"epoch": 120, "loss": 0.468527, "train_acc": 0.8478, "val_acc": 0.8409},
        {"epoch": 140, "loss": 0.466468, "train_acc": 0.8475, "val_acc": 0.8415},
        {"epoch": 160, "loss": 0.461226, "train_acc": 0.8475, "val_acc": 0.8400},
        {"epoch": 180, "loss": 0.459921, "train_acc": 0.8495, "val_acc": 0.8411},
        {"epoch": 200, "loss": 0.458851, "train_acc": 0.8495, "val_acc": 0.8388}
      ]
    },
    "Mamba-S6 4-cls": {
      "params": 24052,
      "architecture": "5-token Mamba (S6)",
      "d_model": 32,
      "d_state": 16,
      "in_channels": 1,
      "layers": 2,
      "epochs": 100,
      "samples": 50000,
      "train_samples": 42483,
      "val_samples": 7497,
      "classify_2d": false,
      "final_loss": 0.255580,
      "best_loss": 0.255537,
      "final_train_acc": 0.9082,
      "final_val_acc": 0.9089,
      "ber_at_20dB": 0.008100,
      "avg_ber": 0.163368,
      "training_history": [
        {"epoch": 1, "loss": 0.319225, "train_acc": 0.9019, "val_acc": 0.9046},
        {"epoch": 10, "loss": 0.270898, "train_acc": 0.9054, "val_acc": 0.9081},
        {"epoch": 20, "loss": 0.267872, "train_acc": 0.9082, "val_acc": 0.9121},
        {"epoch": 30, "loss": 0.263394, "train_acc": 0.9077, "val_acc": 0.9084},
        {"epoch": 40, "loss": 0.259027, "train_acc": 0.9083, "val_acc": 0.9104},
        {"epoch": 50, "loss": 0.258037, "train_acc": 0.9066, "val_acc": 0.9104},
        {"epoch": 60, "loss": 0.257288, "train_acc": 0.9084, "val_acc": 0.9108},
        {"epoch": 70, "loss": 0.256739, "train_acc": 0.9071, "val_acc": 0.9090},
        {"epoch": 80, "loss": 0.256141, "train_acc": 0.9088, "val_acc": 0.9108},
        {"epoch": 90, "loss": 0.255753, "train_acc": 0.9082, "val_acc": 0.9112},
        {"epoch": 100, "loss": 0.255580, "train_acc": 0.9082, "val_acc": 0.9089}
      ]
    },
    "Mamba-S6 16-cls": {
      "params": 24288,
      "architecture": "5-token Mamba (S6)",
      "d_model": 32,
      "d_state": 16,
      "in_channels": 2,
      "layers": 2,
      "epochs": 200,
      "samples": 50000,
      "train_samples": 42500,
      "val_samples": 7500,
      "classify_2d": true,
      "final_loss": 0.442427,
      "best_loss": 0.441585,
      "final_train_acc": 0.8501,
      "final_val_acc": 0.8393,
      "ber_at_20dB": 0.000090,
      "avg_ber": 0.146649,
      "training_history": [
        {"epoch": 1, "loss": 0.817945, "train_acc": 0.8375, "val_acc": 0.8400},
        {"epoch": 20, "loss": 0.512468, "train_acc": 0.8397, "val_acc": 0.8396},
        {"epoch": 40, "loss": 0.494732, "train_acc": 0.8395, "val_acc": 0.8399},
        {"epoch": 60, "loss": 0.482747, "train_acc": 0.8420, "val_acc": 0.8411},
        {"epoch": 80, "loss": 0.476326, "train_acc": 0.8431, "val_acc": 0.8424},
        {"epoch": 100, "loss": 0.467821, "train_acc": 0.8452, "val_acc": 0.8435},
        {"epoch": 120, "loss": 0.462261, "train_acc": 0.8445, "val_acc": 0.8373},
        {"epoch": 140, "loss": 0.457077, "train_acc": 0.8470, "val_acc": 0.8408},
        {"epoch": 160, "loss": 0.452291, "train_acc": 0.8488, "val_acc": 0.8385},
        {"epoch": 180, "loss": 0.447525, "train_acc": 0.8509, "val_acc": 0.8367},
        {"epoch": 200, "loss": 0.442427, "train_acc": 0.8501, "val_acc": 0.8393}
      ]
    },
    "Mamba2 4-cls": {
      "params": 26230,
      "architecture": "5-token Mamba-2 (SSD)",
      "d_model": 32,
      "d_state": 16,
      "in_channels": 1,
      "layers": 2,
      "epochs": 100,
      "samples": 50000,
      "train_samples": 42483,
      "val_samples": 7497,
      "classify_2d": false,
      "final_loss": 0.249102,
      "best_loss": 0.248833,
      "final_train_acc": 0.9091,
      "final_val_acc": 0.9064,
      "ber_at_20dB": 0.008110,
      "avg_ber": 0.163495,
      "training_history": [
        {"epoch": 1, "loss": 0.314192, "train_acc": 0.9060, "val_acc": 0.9049},
        {"epoch": 10, "loss": 0.264139, "train_acc": 0.9086, "val_acc": 0.9065},
        {"epoch": 20, "loss": 0.256880, "train_acc": 0.9088, "val_acc": 0.9081},
        {"epoch": 30, "loss": 0.256060, "train_acc": 0.9089, "val_acc": 0.9076},
        {"epoch": 40, "loss": 0.255444, "train_acc": 0.9091, "val_acc": 0.9073},
        {"epoch": 50, "loss": 0.253946, "train_acc": 0.9092, "val_acc": 0.9064},
        {"epoch": 60, "loss": 0.252801, "train_acc": 0.9090, "val_acc": 0.9084},
        {"epoch": 70, "loss": 0.252155, "train_acc": 0.9088, "val_acc": 0.9068},
        {"epoch": 80, "loss": 0.250853, "train_acc": 0.9086, "val_acc": 0.9037},
        {"epoch": 90, "loss": 0.249797, "train_acc": 0.9078, "val_acc": 0.9057},
        {"epoch": 100, "loss": 0.249102, "train_acc": 0.9091, "val_acc": 0.9064}
      ]
    },
    "Mamba2 16-cls": {
      "params": 26466,
      "architecture": "5-token Mamba-2 (SSD)",
      "d_model": 32,
      "d_state": 16,
      "in_channels": 2,
      "layers": 2,
      "epochs": 200,
      "samples": 50000,
      "train_samples": 42500,
      "val_samples": 7500,
      "classify_2d": true,
      "final_loss": 0.260617,
      "best_loss": 0.259444,
      "final_train_acc": 0.9156,
      "final_val_acc": 0.8013,
      "ber_at_20dB": 0.001970,
      "avg_ber": 0.160593,
      "overfitting_detected": true,
      "overfitting_note": "Train acc 0.916 vs val acc 0.801 — significant gap indicates memorization rather than generalizable 16-class decision boundaries",
      "training_history": [
        {"epoch": 1, "loss": 0.747964, "train_acc": 0.8364, "val_acc": 0.8456},
        {"epoch": 20, "loss": 0.496474, "train_acc": 0.8405, "val_acc": 0.8400},
        {"epoch": 40, "loss": 0.466066, "train_acc": 0.8483, "val_acc": 0.8385},
        {"epoch": 60, "loss": 0.437150, "train_acc": 0.8562, "val_acc": 0.8343},
        {"epoch": 80, "loss": 0.403770, "train_acc": 0.8673, "val_acc": 0.8303},
        {"epoch": 100, "loss": 0.370855, "train_acc": 0.8756, "val_acc": 0.8232},
        {"epoch": 120, "loss": 0.341779, "train_acc": 0.8871, "val_acc": 0.8141},
        {"epoch": 140, "loss": 0.318280, "train_acc": 0.8966, "val_acc": 0.8056},
        {"epoch": 160, "loss": 0.293493, "train_acc": 0.9052, "val_acc": 0.7991},
        {"epoch": 180, "loss": 0.276041, "train_acc": 0.9110, "val_acc": 0.8035},
        {"epoch": 200, "loss": 0.260617, "train_acc": 0.9156, "val_acc": 0.8013}
      ]
    }
  },
  "baselines": {
    "af": {"ber_at_20dB": 0.000630},
    "df": {"ber_at_20dB": 0.000000}
  },
  "summary": {
    "top3": ["VAE 16-cls", "Transformer 16-cls", "MLP 16-cls"],
    "ber_at_20dB": {
      "MLP 4-cls": 0.00811,
      "MLP 16-cls": 0.00002,
      "VAE 4-cls": 0.49919,
      "VAE 16-cls": 0.00000,
      "CGAN 4-cls": 0.00811,
      "CGAN 16-cls": 0.50043,
      "Hybrid 4-cls": 0.25017,
      "Hybrid 16-cls": 0.37553,
      "Transformer 4-cls": 0.00810,
      "Transformer 16-cls": 0.00001,
      "Mamba-S6 4-cls": 0.00810,
      "Mamba-S6 16-cls": 0.00009,
      "Mamba2 4-cls": 0.00811,
      "Mamba2 16-cls": 0.00197,
      "AF": 0.00063,
      "DF": 0.00000
    }
  }
}
